flomo/__init__.py
flomo/cli.py
flomo-1.0.0a0.dist-info/licenses/LICENCE
flomo-1.0.0a0.dist-info/METADATA
flomo-1.0.0a0.dist-info/WHEEL
flomo-1.0.0a0.dist-info/entry_points.txt
flomo-1.0.0a0.dist-info/top_level.txt
flomo-1.0.0a0.dist-info/RECORD
