Metadata-Version: 2.4
Name: flomo
Version: 1.0.0a0
Summary: Flomo API (third party)
Home-page: https://github.com/Benature/flomo
Author: Benature Wang
Author-email: benature246@gmail.com
Classifier: Programming Language :: Python :: 3.7
Classifier: License :: OSI Approved :: MIT License
Classifier: Operating System :: OS Independent
Requires-Python: >=3.7
License-File: LICENCE
Requires-Dist: requests
Requires-Dist: bs4
Requires-Dist: html2text
Requires-Dist: twine
Dynamic: author
Dynamic: author-email
Dynamic: classifier
Dynamic: description
Dynamic: description-content-type
Dynamic: home-page
Dynamic: license-file
Dynamic: requires-dist
Dynamic: requires-python
Dynamic: summary
